methodwebtest/__init__.py
methodwebtest/core/__init__.py
methodwebtest/core/datetime_utils.py
methodwebtest/core/pydantic_utilities.py
methodwebtest/core/serialization.py
methodwebtest/py.typed
methodwebtest/resources/__init__.py
methodwebtest/resources/configs/__init__.py
methodwebtest/resources/configs/body_xml_rpc_function_auth_config.py
methodwebtest/resources/configs/header_buffer_overflow_config.py
methodwebtest/resources/configs/header_misconfiguration_config.py
methodwebtest/resources/configs/header_options_bleed_config.py
methodwebtest/resources/configs/header_server_overload_config.py
methodwebtest/resources/configs/header_user_agent_config.py
methodwebtest/resources/configs/injection_location.py
methodwebtest/resources/configs/multi_injection_config.py
methodwebtest/resources/configs/path_crlf_config.py
methodwebtest/resources/configs/path_mod_file_config.py
methodwebtest/resources/configs/path_traversal_config.py
methodwebtest/resources/configs/query_reverse_proxy_config.py
methodwebtest/resources/report/__init__.py
methodwebtest/resources/report/attempt_info.py
methodwebtest/resources/report/engine_config.py
methodwebtest/resources/report/header_misconfiguration_engine_config.py
methodwebtest/resources/report/injection_engine_config.py
methodwebtest/resources/report/path_traversal_engine_config.py
methodwebtest/resources/report/report.py
methodwebtest/resources/report/target_info.py
methodwebtest/resources/request/__init__.py
methodwebtest/resources/request/body_event.py
methodwebtest/resources/request/event_type.py
methodwebtest/resources/request/header_event.py
methodwebtest/resources/request/http_method.py
methodwebtest/resources/request/multi_event.py
methodwebtest/resources/request/path_event.py
methodwebtest/resources/request/query_event.py
methodwebtest/resources/request/request_info.py
methodwebtest/resources/request/request_params.py
methodwebtest-0.0.25.dist-info/METADATA
methodwebtest-0.0.25.dist-info/WHEEL
methodwebtest-0.0.25.dist-info/RECORD
